Metadata-Version: 2.4
Name: mcp-server-qdrant
Version: 0.8.0
Summary: MCP server for retrieving context from a Qdrant vector database
License-Expression: Apache-2.0
License-File: LICENSE
Requires-Python: >=3.10
Requires-Dist: fastembed>=0.6.0
Requires-Dist: fastmcp>=2.7.0
Requires-Dist: pydantic>=2.10.6
Requires-Dist: qdrant-client>=1.12.0
